{
	"info": {
		"_postman_id": "07a158ea-c0e5-41a8-a0e6-c86510a35557",
		"name": "Reqres.in",
		"schema": "https://schema.getpostman.com/json/collection/v2.1.0/collection.json",
		"_exporter_id": "21780631"
	},
	"item": [
		{
			"name": "GET",
			"item": [
				{
					"name": "LIST USERS",
					"event": [
						{
							"listen": "test",
							"script": {
								"exec": [
									"pm.test(\"Verify status code is 200\", function () {\r",
									"    pm.response.to.have.status(200);\r",
									"});\r",
									"\r",
									"pm.test(\"Verify that first_name equals Michael\", function () {\r",
									"    var jsonData = pm.response.json();\r",
									"    pm.expect(jsonData.first_name).to.eql(Michael);\r",
									"});\r",
									""
								],
								"type": "text/javascript"
							}
						}
					],
					"request": {
						"method": "GET",
						"header": [],
						"url": {
							"raw": "https://reqres.in/api/users?page=2",
							"protocol": "https",
							"host": [
								"reqres",
								"in"
							],
							"path": [
								"api",
								"users"
							],
							"query": [
								{
									"key": "page",
									"value": "2"
								}
							]
						}
					},
					"response": []
				},
				{
					"name": "LIST USERS 2",
					"event": [
						{
							"listen": "test",
							"script": {
								"exec": [
									"pm.test(\"Verify status code is 200\", function () {\r",
									"    pm.response.to.have.status(200);\r",
									"});\r",
									"\r",
									"pm.test(\"Verify that page equals 2\", function () {\r",
									"    var jsonData = pm.response.json();\r",
									"    pm.expect(jsonData.page).to.eql(2);\r",
									"});\r",
									""
								],
								"type": "text/javascript"
							}
						}
					],
					"request": {
						"method": "GET",
						"header": [],
						"url": {
							"raw": "https://reqres.in/api/users?page=2",
							"protocol": "https",
							"host": [
								"reqres",
								"in"
							],
							"path": [
								"api",
								"users"
							],
							"query": [
								{
									"key": "page",
									"value": "2"
								}
							]
						}
					},
					"response": []
				},
				{
					"name": "SINGLE USER",
					"request": {
						"method": "GET",
						"header": [],
						"url": {
							"raw": "https://reqres.in/api/users/2",
							"protocol": "https",
							"host": [
								"reqres",
								"in"
							],
							"path": [
								"api",
								"users",
								"2"
							]
						}
					},
					"response": []
				},
				{
					"name": "SINGLE USER NOT FOUND",
					"request": {
						"method": "GET",
						"header": [],
						"url": {
							"raw": "https://reqres.in/api/users/23",
							"protocol": "https",
							"host": [
								"reqres",
								"in"
							],
							"path": [
								"api",
								"users",
								"23"
							]
						}
					},
					"response": []
				},
				{
					"name": "LIST <RESOURCE>",
					"request": {
						"method": "GET",
						"header": [],
						"url": {
							"raw": "https://reqres.in/api/unknown",
							"protocol": "https",
							"host": [
								"reqres",
								"in"
							],
							"path": [
								"api",
								"unknown"
							]
						}
					},
					"response": []
				},
				{
					"name": "SINGLE <RESOURCE>",
					"request": {
						"method": "GET",
						"header": [],
						"url": {
							"raw": "https://reqres.in/api/unknown/2",
							"protocol": "https",
							"host": [
								"reqres",
								"in"
							],
							"path": [
								"api",
								"unknown",
								"2"
							]
						}
					},
					"response": []
				},
				{
					"name": "DELAYED RESPONSE",
					"request": {
						"method": "GET",
						"header": [],
						"url": {
							"raw": "https://reqres.in/api/users?delay=3",
							"protocol": "https",
							"host": [
								"reqres",
								"in"
							],
							"path": [
								"api",
								"users"
							],
							"query": [
								{
									"key": "delay",
									"value": "3"
								}
							]
						}
					},
					"response": []
				}
			]
		},
		{
			"name": "POST",
			"item": [
				{
					"name": "CREATE",
					"request": {
						"method": "POST",
						"header": [],
						"body": {
							"mode": "raw",
							"raw": "{\r\n    \"name\": \"telepus\",\r\n    \"job\": \"TV\"\r\n}",
							"options": {
								"raw": {
									"language": "json"
								}
							}
						},
						"url": {
							"raw": "https://reqres.in/api/users",
							"protocol": "https",
							"host": [
								"reqres",
								"in"
							],
							"path": [
								"api",
								"users"
							]
						}
					},
					"response": []
				},
				{
					"name": "REGISTER - SUCCESSFUL",
					"request": {
						"method": "POST",
						"header": [],
						"body": {
							"mode": "raw",
							"raw": "{\r\n    \"email\": \"eve.holt@reqres.in\",\r\n    \"password\": \"pistol\"\r\n}",
							"options": {
								"raw": {
									"language": "json"
								}
							}
						},
						"url": {
							"raw": "https://reqres.in/api/register",
							"protocol": "https",
							"host": [
								"reqres",
								"in"
							],
							"path": [
								"api",
								"register"
							]
						}
					},
					"response": []
				},
				{
					"name": "REGISTER - UNSUCCESSFUL",
					"request": {
						"method": "POST",
						"header": [],
						"body": {
							"mode": "raw",
							"raw": "{\r\n    \"email\": \"sydney@fife\"\r\n}",
							"options": {
								"raw": {
									"language": "json"
								}
							}
						},
						"url": {
							"raw": "https://reqres.in/api/register",
							"protocol": "https",
							"host": [
								"reqres",
								"in"
							],
							"path": [
								"api",
								"register"
							]
						}
					},
					"response": []
				},
				{
					"name": "LOGIN - SUCCESSFUL",
					"request": {
						"method": "POST",
						"header": [],
						"body": {
							"mode": "raw",
							"raw": "{\r\n    \"email\": \"eve.holt@reqres.in\",\r\n    \"password\": \"cityslicka\"\r\n}",
							"options": {
								"raw": {
									"language": "json"
								}
							}
						},
						"url": {
							"raw": "https://reqres.in/api/login",
							"protocol": "https",
							"host": [
								"reqres",
								"in"
							],
							"path": [
								"api",
								"login"
							]
						}
					},
					"response": []
				},
				{
					"name": "LOGIN - UNSUCCESSFUL",
					"request": {
						"method": "POST",
						"header": [],
						"body": {
							"mode": "raw",
							"raw": "{\r\n    \"email\": \"peter@klaven\"\r\n}",
							"options": {
								"raw": {
									"language": "json"
								}
							}
						},
						"url": {
							"raw": "https://reqres.in/api/login",
							"protocol": "https",
							"host": [
								"reqres",
								"in"
							],
							"path": [
								"api",
								"login"
							]
						}
					},
					"response": []
				}
			]
		},
		{
			"name": "PACTH",
			"item": [
				{
					"name": "UPDATE",
					"request": {
						"method": "PATCH",
						"header": [],
						"body": {
							"mode": "raw",
							"raw": "{\r\n    \"name\": \"Telepusik\",\r\n    \"job\": \"president\"\r\n}",
							"options": {
								"raw": {
									"language": "json"
								}
							}
						},
						"url": {
							"raw": "https://reqres.in/api/users/2",
							"protocol": "https",
							"host": [
								"reqres",
								"in"
							],
							"path": [
								"api",
								"users",
								"2"
							]
						}
					},
					"response": []
				}
			]
		},
		{
			"name": "DELETE",
			"item": [
				{
					"name": "Delete",
					"request": {
						"method": "DELETE",
						"header": [],
						"url": {
							"raw": "https://reqres.in/api/users/23",
							"protocol": "https",
							"host": [
								"reqres",
								"in"
							],
							"path": [
								"api",
								"users",
								"23"
							]
						}
					},
					"response": []
				}
			]
		},
		{
			"name": "PUT",
			"item": [
				{
					"name": "UPDATE",
					"request": {
						"method": "PUT",
						"header": [],
						"body": {
							"mode": "raw",
							"raw": "{\r\n    \"name\": \"morpheus\",\r\n    \"job\": \"zion resident\"\r\n}"
						},
						"url": {
							"raw": "https://reqres.in/api/users/2",
							"protocol": "https",
							"host": [
								"reqres",
								"in"
							],
							"path": [
								"api",
								"users",
								"2"
							]
						}
					},
					"response": []
				}
			]
		}
	]
}